manchester_codec/__init__.py
manchester_codec/codec.py
manchester_codec-0.3.0.dist-info/METADATA
manchester_codec-0.3.0.dist-info/WHEEL
manchester_codec-0.3.0.dist-info/licenses/LICENSE
manchester_codec-0.3.0.dist-info/RECORD
