Metadata-Version: 2.4
Name: manchester_codec
Version: 0.3.0
Summary: Manchester line encoder/decoder supporting IEEE and Thomas variants.
Project-URL: Homepage, https://www.fevaris.com
Project-URL: Documentation, https://github.com/eneserginth/manchester_codec#readme
Project-URL: Source, https://github.com/eneserginth/manchester_codec
Project-URL: Issues, https://github.com/eneserginth/manchester_codec/issues
Author-email: Emir Enes ERGİN <enes.erginth@gmail.com>
License: MIT License
License-File: LICENSE
Keywords: decoding,encoding,ieee,manchester,thomas
Classifier: Development Status :: 4 - Beta
Classifier: Intended Audience :: Developers
Classifier: License :: OSI Approved :: MIT License
Classifier: Programming Language :: Python
Classifier: Programming Language :: Python :: 3
Classifier: Programming Language :: Python :: 3 :: Only
Classifier: Programming Language :: Python :: 3.9
Classifier: Programming Language :: Python :: 3.10
Classifier: Programming Language :: Python :: 3.11
Classifier: Programming Language :: Python :: 3.12
Classifier: Topic :: Software Development :: Libraries
Classifier: Topic :: System :: Networking
Classifier: Typing :: Typed
Requires-Python: >=3.9
Provides-Extra: dev
Requires-Dist: pytest>=7.4; extra == 'dev'
